fluxtune/__init__.py
fluxtune/binpredalg.py
fluxtune/experts.py
fluxtune-0.1.2.dist-info/LICENSE
fluxtune-0.1.2.dist-info/METADATA
fluxtune-0.1.2.dist-info/WHEEL
fluxtune-0.1.2.dist-info/top_level.txt
fluxtune-0.1.2.dist-info/RECORD
