Metadata-Version: 2.1
Name: fluxtune
Version: 0.1.2
Summary: Flux tune is a library intended to implemnet various online machine learning algorithms and agents
Home-page: https://github.com/Pradeep8802/fluxtune
Author: SAI PRADEEP
Author-email: saipradeepirgp@gmail.com
License: MIT
Classifier: Development Status :: 3 - Alpha
Classifier: Intended Audience :: Developers
Classifier: License :: OSI Approved :: MIT License
Classifier: Programming Language :: Python :: 3
Classifier: Programming Language :: Python :: 3.7
Classifier: Programming Language :: Python :: 3.8
Classifier: Programming Language :: Python :: 3.9
Classifier: Programming Language :: Python :: 3.10
Requires-Python: >=3.7
License-File: LICENSE
Requires-Dist: numpy >=1.18.0
